convert_to_confluence_wiki/__init__.py
convert_to_confluence_wiki/convert_to_confluence.py
convert_to_confluence-1.0.1.dist-info/LICENSE
convert_to_confluence-1.0.1.dist-info/METADATA
convert_to_confluence-1.0.1.dist-info/WHEEL
convert_to_confluence-1.0.1.dist-info/top_level.txt
convert_to_confluence-1.0.1.dist-info/RECORD
