Metadata-Version: 2.2
Name: convert_to_confluence
Version: 1.0.1
Summary: A Python package to convert Markdown to Confluence format.
Home-page: https://github.com/AryamanGurjar/Confluence-Wiki-Formatter-Package
Author: Aryaman Gurjar
Author-email: aryamangurjar6@gmail.com
Classifier: Programming Language :: Python :: 3
Classifier: License :: OSI Approved :: MIT License
Classifier: Operating System :: OS Independent
Requires-Python: >=3.6
License-File: LICENSE
Dynamic: author
Dynamic: author-email
Dynamic: classifier
Dynamic: description
Dynamic: description-content-type
Dynamic: home-page
Dynamic: requires-python
Dynamic: summary
